asgi_prometheus/__init__.py
asgi_prometheus/py.typed
asgi_prometheus-1.2.3.dist-info/LICENSE
asgi_prometheus-1.2.3.dist-info/METADATA
asgi_prometheus-1.2.3.dist-info/WHEEL
asgi_prometheus-1.2.3.dist-info/top_level.txt
asgi_prometheus-1.2.3.dist-info/RECORD
