Metadata-Version: 2.1
Name: asgi-prometheus
Version: 1.2.3
Summary: Support Prometheus metrics for ASGI applications
Author-email: Kirill Klenov <horneds@gmail.com>
License: MIT License
Project-URL: homepage, https://github.com/klen/asgi-prometheus
Project-URL: repository, https://github.com/klen/asgi-prometheus
Keywords: asyncio,trio,curio,asgi,prometheus
Classifier: Development Status :: 5 - Production/Stable
Classifier: Intended Audience :: Developers
Classifier: License :: OSI Approved :: MIT License
Classifier: Programming Language :: Python
Classifier: Programming Language :: Python :: 3
Classifier: Programming Language :: Python :: 3.9
Classifier: Programming Language :: Python :: 3.10
Classifier: Programming Language :: Python :: 3.11
Classifier: Programming Language :: Python :: 3.12
Classifier: Topic :: Internet :: WWW/HTTP
Classifier: Framework :: AsyncIO
Classifier: Framework :: Trio
Requires-Python: >=3.9
License-File: LICENSE
Requires-Dist: asgi-tools >=0.71.0
Requires-Dist: prometheus-client >=0.10.1
Provides-Extra: dev
Requires-Dist: bump2version ; extra == 'dev'
Requires-Dist: tox ; extra == 'dev'
Requires-Dist: pre-commit ; extra == 'dev'
Requires-Dist: refurb ; (python_version >= "3.9") and extra == 'dev'
Provides-Extra: tests
Requires-Dist: pytest ; extra == 'tests'
Requires-Dist: pytest-aio[curio,trio] >=1.1.0 ; extra == 'tests'
Requires-Dist: ruff ; extra == 'tests'
Requires-Dist: pytest-mypy ; (implementation_name == "cpython") and extra == 'tests'
